sdf_wot_converter/__init__.py
sdf_wot_converter/__main__.py
sdf_wot_converter/cli/__init__.py
sdf_wot_converter/converters/__init__.py
sdf_wot_converter/converters/jsonschema.py
sdf_wot_converter/converters/sdf_to_tm.py
sdf_wot_converter/converters/td_to_tm.py
sdf_wot_converter/converters/tm_to_sdf.py
sdf_wot_converter/converters/tm_to_td.py
sdf_wot_converter/converters/utility.py
sdf_wot_converter/converters/wot_common.py
sdf_wot_converter/validation/__init__.py
sdf_wot_converter/validation/sdf_framework_schema.py
sdf_wot_converter/validation/sdf_validation_schema.py
sdf_wot_converter/validation/td_schema.py
sdf_wot_converter/validation/tm_schema.py
sdf_wot_converter-1.10.0.dist-info/LICENSE
sdf_wot_converter-1.10.0.dist-info/METADATA
sdf_wot_converter-1.10.0.dist-info/WHEEL
sdf_wot_converter-1.10.0.dist-info/entry_points.txt
sdf_wot_converter-1.10.0.dist-info/top_level.txt
sdf_wot_converter-1.10.0.dist-info/RECORD
