Metadata-Version: 2.1
Name: sdf-wot-converter
Version: 1.10.0
Summary: Converter between WoT TD and SDF (including protocol bindings).
Home-page: https://github.com/JKRhb/sdf-wot-converter-py
Author: Jan Romann
Author-email: jan.romann@uni-bremen.de
Project-URL: Bug Tracker, https://github.com/JKRhb/sdf-wot-converter-py/issues
Classifier: Programming Language :: Python :: 3
Classifier: License :: OSI Approved :: MIT License
Classifier: Operating System :: OS Independent
Requires-Python: >=3.7
License-File: LICENSE
Requires-Dist: jsonschema (<5,>=4.6.0)
Requires-Dist: jsonpointer (<3,>=2.3)
Requires-Dist: json-merge-patch (<1,>=0.2.0)
Requires-Dist: validators (<1,>=0.20.0)
